allyoucanuse/__init__.py
allyoucanuse/etc/__init__.py
allyoucanuse/etc/calendar.py
allyoucanuse/etc/hashing.py
allyoucanuse/io/__init__.py
allyoucanuse/io/file_io.py
allyoucanuse-1.0.5.dist-info/LICENSE
allyoucanuse-1.0.5.dist-info/METADATA
allyoucanuse-1.0.5.dist-info/WHEEL
allyoucanuse-1.0.5.dist-info/top_level.txt
allyoucanuse-1.0.5.dist-info/RECORD
