Metadata-Version: 2.1
Name: allyoucanuse
Version: 1.0.5
Summary: One-liners of everything - a hodge-podge of python tools
Home-page: https://github.com/kunlubrain/allyoucanuse
Author: diebridge
Author-email: f_flare@live.cn
License: UNKNOWN
Platform: UNKNOWN
Classifier: Programming Language :: Python :: 3
Classifier: License :: OSI Approved :: MIT License
Classifier: Operating System :: OS Independent
License-File: LICENSE
Requires-Dist: jsonlines
